mccode_antlr/__init__.py
mccode_antlr/test.py
mccode_antlr/utils.py
mccode_antlr/version.py
mccode_antlr/assembler/__init__.py
mccode_antlr/assembler/assembler.py
mccode_antlr/cli/__init__.py
mccode_antlr/cli/commands.py
mccode_antlr/cli/management.py
mccode_antlr/common/__init__.py
mccode_antlr/common/block.py
mccode_antlr/common/expression.py
mccode_antlr/common/metadata.py
mccode_antlr/common/mode.py
mccode_antlr/common/parameters.py
mccode_antlr/common/textwrap.py
mccode_antlr/common/utilities.py
mccode_antlr/common/visitor.py
mccode_antlr/comp/__init__.py
mccode_antlr/comp/comp.py
mccode_antlr/comp/visitor.py
mccode_antlr/compiler/__init__.py
mccode_antlr/compiler/c.py
mccode_antlr/compiler/check.py
mccode_antlr/config/__init__.py
mccode_antlr/config/config_default.yaml
mccode_antlr/config/fallback.py
mccode_antlr/config/platforms.yaml
mccode_antlr/grammar/C.interp
mccode_antlr/grammar/C.tokens
mccode_antlr/grammar/CLexer.interp
mccode_antlr/grammar/CLexer.py
mccode_antlr/grammar/CLexer.tokens
mccode_antlr/grammar/CListener.py
mccode_antlr/grammar/CParser.py
mccode_antlr/grammar/CVisitor.py
mccode_antlr/grammar/McComp.interp
mccode_antlr/grammar/McComp.tokens
mccode_antlr/grammar/McCompLexer.interp
mccode_antlr/grammar/McCompLexer.py
mccode_antlr/grammar/McCompLexer.tokens
mccode_antlr/grammar/McCompParser.py
mccode_antlr/grammar/McCompVisitor.py
mccode_antlr/grammar/McInstr.interp
mccode_antlr/grammar/McInstr.tokens
mccode_antlr/grammar/McInstrLexer.interp
mccode_antlr/grammar/McInstrLexer.py
mccode_antlr/grammar/McInstrLexer.tokens
mccode_antlr/grammar/McInstrParser.py
mccode_antlr/grammar/McInstrVisitor.py
mccode_antlr/grammar/__init__.py
mccode_antlr/grammar/mccode_parse.py
mccode_antlr/grammar/mccomp_parse.py
mccode_antlr/grammar/mcinstr_parse.py
mccode_antlr/instr/__init__.py
mccode_antlr/instr/group.py
mccode_antlr/instr/instance.py
mccode_antlr/instr/instr.py
mccode_antlr/instr/jump.py
mccode_antlr/instr/orientation.py
mccode_antlr/instr/visitor.py
mccode_antlr-0.17.1.dist-info/licenses/LICENSE
mccode_antlr-0.17.1.dist-info/METADATA
mccode_antlr-0.17.1.dist-info/WHEEL
mccode_antlr-0.17.1.dist-info/entry_points.txt
mccode_antlr-0.17.1.dist-info/top_level.txt
mccode_antlr-0.17.1.dist-info/RECORD
