Metadata-Version: 2.4
Name: mccode-antlr
Version: 0.17.1
Summary: ANTLR4 grammars for McStas and McXtrace
Author-email: Gregory Tucker <gregory.tucker@ess.eu>
License: BSD-3-Clause
Project-URL: Homepage, https://github.com/mccode-dev/mccode-antlr
Classifier: License :: OSI Approved :: BSD License
Classifier: Programming Language :: Python :: 3
Classifier: Programming Language :: Python :: 3 :: Only
Classifier: Programming Language :: Python :: 3.10
Classifier: Programming Language :: Python :: 3.11
Classifier: Programming Language :: Python :: 3.12
Classifier: Programming Language :: Python :: 3.13
Classifier: Programming Language :: Python :: 3.14
Requires-Python: >=3.9
License-File: LICENSE
Requires-Dist: antlr4-python3-runtime>=4.13.2
Requires-Dist: numpy>=2
Requires-Dist: pooch>=1.7.0
Requires-Dist: confuse>=2.2.0
Requires-Dist: typing-extensions>=4.15.0
Requires-Dist: loguru>=0.7.2
Requires-Dist: gitpython>=3.1.43
Requires-Dist: msgspec>=0.19.0
Requires-Dist: packaging
Requires-Dist: pyyaml
Provides-Extra: test
Requires-Dist: gputil==1.4.0; extra == "test"
Requires-Dist: pytest; extra == "test"
Provides-Extra: hdf5
Requires-Dist: h5py>=3.11.0; extra == "hdf5"
Provides-Extra: mcpl
Requires-Dist: mcpl>=2.2.0; extra == "mcpl"
Dynamic: license-file
